<annotation>
	<folder>h</folder>
	<filename>frame1624969205cal.png</filename>
	<path>/home/sarath/Object-Detection-API/dataset/calibrated/h/frame1624969205cal.png</path>
	<source>
		<database>Unknown</database>
	</source>
	<size>
		<width>1504</width>
		<height>660</height>
		<depth>3</depth>
	</size>
	<segmented>0</segmented>
	<object>
		<name>white-bishop</name>
		<pose>Unspecified</pose>
		<truncated>0</truncated>
		<difficult>0</difficult>
		<bndbox>
			<xmin>642</xmin>
			<ymin>247</ymin>
			<xmax>684</xmax>
			<ymax>287</ymax>
		</bndbox>
	</object>
	<object>
		<name>white-king</name>
		<pose>Unspecified</pose>
		<truncated>0</truncated>
		<difficult>0</difficult>
		<bndbox>
			<xmin>454</xmin>
			<ymin>238</ymin>
			<xmax>512</xmax>
			<ymax>285</ymax>
		</bndbox>
	</object>
	<object>
		<name>black-king</name>
		<pose>Unspecified</pose>
		<truncated>0</truncated>
		<difficult>0</difficult>
		<bndbox>
			<xmin>457</xmin>
			<ymin>299</ymin>
			<xmax>512</xmax>
			<ymax>337</ymax>
		</bndbox>
	</object>
	<object>
		<name>black-bishop</name>
		<pose>Unspecified</pose>
		<truncated>0</truncated>
		<difficult>0</difficult>
		<bndbox>
			<xmin>532</xmin>
			<ymin>236</ymin>
			<xmax>571</xmax>
			<ymax>277</ymax>
		</bndbox>
	</object>
	<object>
		<name>black-queen</name>
		<pose>Unspecified</pose>
		<truncated>0</truncated>
		<difficult>0</difficult>
		<bndbox>
			<xmin>579</xmin>
			<ymin>235</ymin>
			<xmax>624</xmax>
			<ymax>280</ymax>
		</bndbox>
	</object>
	<object>
		<name>white-queen</name>
		<pose>Unspecified</pose>
		<truncated>0</truncated>
		<difficult>0</difficult>
		<bndbox>
			<xmin>576</xmin>
			<ymin>292</ymin>
			<xmax>624</xmax>
			<ymax>338</ymax>
		</bndbox>
	</object>
</annotation>
